Workbook

Sheet Management_Summary
A1: Management Summary
F2: 2025 Actual vs 2026 Base Plan (Total for all Stores)
A3: Assumption | B3: Downside | C3: Base | D3: Upside | F3: Metric | G3: 2025 Actual | H3: 2026 Base Plan | I3: Change
A4: Sales Growth % | B4: -0.02 | C4: 0.03 | D4: 0.06 | F4: Sales | G4: =historical_actuals3[[#Totals],[net_sales]] -> 474595610 | H4: ='2026_COGS_GROSS_PROFIT Plan'!E292 -> 4.8883348e+08 | I4: =(H4-G4)/G4 -> 0.03
A5: COGS Inflation % | B5: 0.05 | C5: 0.03 | D5: 0.01 | F5: Gross Profit | G5: =historical_actuals3[[#Totals],[gross_profit]] -> 102214615 | H5: ='2026_COGS_GROSS_PROFIT Plan'!G292 -> 93774481 | I5: =(H5-G5)/G5 -> -0.082572676
A6: Labour Cost Increase % | B6: 0.06 | C6: 0.04 | D6: 0.03 | F6: Gross Margin | G6: =historical_actuals3[[#Totals],[gross_margin_%]] -> 0.21537202 | H6: ='2026_COGS_GROSS_PROFIT Plan'!H292 -> 0.19183318 | I6: =(H6-G6) -> -0.023538839
A7: Operating Expense Increase % | B7: 0.05 | C7: 0.03 | D7: 0.02 | F7: Operating Profit | G7: =historical_actuals3[[#Totals],[operating_profit]] -> 57311222 | H7: ='2026_COGS_GROSS_PROFIT Plan'!K292 -> 47364525 | I7: =(H7-G7)/G7 -> -0.17355583
A8: Metric | B8: 2026 Downside | C8: 2026 Base | D8: 2026 Upside | F8: Operating margin | G8: =historical_actuals3[[#Totals],[operating_margin_%]] -> 0.12075801 | H8: ='2026_COGS_GROSS_PROFIT Plan'!L291 -> 0.185259 | I8: =(H8-G8) -> 0.064500993
A9: Planned Sales | B9: =$G$4*(1+Management_Summary!B4) -> 4.651037e+08 | C9: =$G$4*(1+Management_Summary!C4) -> 4.8883348e+08 | D9: =$G$4*(1+Management_Summary!D4) -> 5.0307135e+08 | F9: Operating margin | G9: =historical_actuals3[[#Totals],[operating_margin_%]] -> 0.12075801 | H9: ='2026_COGS_GROSS_PROFIT Plan'!L292 -> 0.096892966 | I9: =(H9-G9) -> -0.023865046
A10: Planned COGS | B10: ='2026_COGS_GROSS_PROFIT Plan'!$D$292*(1+B4)*(1+Management_Summary!B5) -> 3.8318004e+08 | C10: ='2026_COGS_GROSS_PROFIT Plan'!$D$292*(1+C4)*(1+Management_Summary!C5) -> 3.95059e+08 | D10: ='2026_COGS_GROSS_PROFIT Plan'!$D$292*(1+D4)*(1+Management_Summary!D5) -> 3.9867109e+08
A11: Gross Profit | B11: =B9-B10 -> 81923654 | C11: =C9-C10 -> 93774481 | D11: =D9-D10 -> 1.0440025e+08
A12: Gross Margin % | B12: =(B11/B9) -> 0.17614062 | C12: =(C11/C9) -> 0.19183318 | D12: =(D11/D9) -> 0.20752574
A13: Labour Cost | B13: =historical_actuals!$G$292*(1+Management_Summary!B6) -> 16902837 | C13: =historical_actuals!$G$292*(1+Management_Summary!C6) -> 16583915 | D13: =historical_actuals!$G$292*(1+Management_Summary!D6) -> 16424454
A14: Operating Expenses | B14: =historical_actuals!$H$292*(1+B7) -> 30405187 | C14: =historical_actuals!$H$292*(1+Management_Summary!C7) -> 29826040 | D14: =historical_actuals!$H$292*(1+Management_Summary!D7) -> 29536467
A15: Operating Profit | B15: =B11-B13-B14 -> 34615631 | C15: =C11-C13-C14 -> 47364525 | D15: =D11-D13-D14 -> 58439332
A16: Operating Margin % | B16: =B15/B9 -> 0.074425619 | C16: =C15/C9 -> 0.096892966 | D16: =D15/D9 -> 0.1161651
A18: Key Takaway

Sheet 2026_COGS_GROSS_PROFIT Plan
A1: month_year | B1: store_id | C1: 2025_sales | D1: 2025_cogs | E1: planned_sales | F1: planned_cogs | G1: planned_gross_profit | H1: gross_margin | I1: planned_labour_cost | J1: planned_operating_expenses | K1: operating_profit | L1: operating_margin_%
A2: {=_xlfn.HSTACK(SUBSTITUTE(historical_actuals[month_year],"-25","-26"),historical_actuals[store_id],historical_actuals[net_sales],historical_actuals[cogs])} -> Jan-26 | B2: ST001 | C2: 1629783 | D2: 1296230 | E2: =C2*(1+Assumptions!$B$12) -> 1678676.5 | F2: =D2*(1+Assumptions!$B$12)*(1+Assumptions!$B$13) -> 1375170.4 | G2: =E2-F2 -> 303506.08 | H2: =IFERROR(G2/E2,0) -> 0.18080082 | I2: {=historical_actuals[labour_cost]*(1+Assumptions!B14)} -> 71263.473 | J2: {=historical_actuals3[operating_expenses]*(1+Assumptions!B15)} -> 138112.16 | K2: =E2-F2-I2-J2 -> 94130.446 | L2: =IFERROR(K2/E2,0) -> 0.056074203
A3: Jan-26 | B3: ST002 | C3: 1617193 | D3: 1283300 | E3: =C3*(1+Assumptions!$B$12) -> 1665708.8 | F3: =D3*(1+Assumptions!$B$12)*(1+Assumptions!$B$13) -> 1361453 | G3: =E3-F3 -> 304255.82 | H3: =IFERROR(G3/E3,0) -> 0.18265847 | I3: 70718.326 | J3: 131024.25 | K3: =E3-F3-I3-J3 -> 102513.24 | L3: =IFERROR(K3/E3,0) -> 0.061543317
A4: Jan-26 | B4: ST003 | C4: 1633880 | D4: 1303972 | E4: =C4*(1+Assumptions!$B$12) -> 1682896.4 | F4: =D4*(1+Assumptions!$B$12)*(1+Assumptions!$B$13) -> 1383383.9 | G4: =E4-F4 -> 299512.51 | H4: =IFERROR(G4/E4,0) -> 0.17797442 | I4: 72203.529 | J4: 128848.35 | K4: =E4-F4-I4-J4 -> 98460.622 | L4: =IFERROR(K4/E4,0) -> 0.058506645
A5: Jan-26 | B5: ST004 | C5: 1620996 | D5: 1311164 | E5: =C5*(1+Assumptions!$B$12) -> 1669625.9 | F5: =D5*(1+Assumptions!$B$12)*(1+Assumptions!$B$13) -> 1391013.9 | G5: =E5-F5 -> 278611.99 | H5: =IFERROR(G5/E5,0) -> 0.16687091 | I5: 69415.694 | J5: 141388.44 | K5: =E5-F5-I5-J5 -> 67807.858 | L5: =IFERROR(K5/E5,0) -> 0.040612606
A6: Jan-26 | B6: ST005 | C6: 1540837 | D6: 1232753 | E6: =C6*(1+Assumptions!$B$12) -> 1587062.1 | F6: =D6*(1+Assumptions!$B$12)*(1+Assumptions!$B$13) -> 1307827.7 | G6: =E6-F6 -> 279234.45 | H6: =IFERROR(G6/E6,0) -> 0.17594425 | I6: 74002.968 | J6: 123111.77 | K6: =E6-F6-I6-J6 -> 82119.715 | L6: =IFERROR(K6/E6,0) -> 0.051743227
A7: Jan-26 | B7: ST006 | C7: 1490262 | D7: 1174186 | E7: =C7*(1+Assumptions!$B$12) -> 1534969.9 | F7: =D7*(1+Assumptions!$B$12)*(1+Assumptions!$B$13) -> 1245693.9 | G7: =E7-F7 -> 289275.93 | H7: =IFERROR(G7/E7,0) -> 0.18845708 | I7: 73544.858 | J7: 118570.49 | K7: =E7-F7-I7-J7 -> 97160.585 | L7: =IFERROR(K7/E7,0) -> 0.063298041
A8: Jan-26 | B8: ST007 | C8: 1722278 | D8: 1362688 | E8: =C8*(1+Assumptions!$B$12) -> 1773946.3 | F8: =D8*(1+Assumptions!$B$12)*(1+Assumptions!$B$13) -> 1445675.7 | G8: =E8-F8 -> 328270.64 | H8: =IFERROR(G8/E8,0) -> 0.18505105 | I8: 72711.86 | J8: 116360.88 | K8: =E8-F8-I8-J8 -> 139197.9 | L8: =IFERROR(K8/E8,0) -> 0.078467931
A9: Jan-26 | B9: ST008 | C9: 1766395 | D9: 1385977 | E9: =C9*(1+Assumptions!$B$12) -> 1819386.9 | F9: =D9*(1+Assumptions!$B$12)*(1+Assumptions!$B$13) -> 1470383 | G9: =E9-F9 -> 349003.85 | H9: =IFERROR(G9/E9,0) -> 0.19182498 | I9: 72633.319 | J9: 124973.76 | K9: =E9-F9-I9-J9 -> 151396.77 | L9: =IFERROR(K9/E9,0) -> 0.083213072
A10: Jan-26 | B10: ST009 | C10: 1664236 | D10: 1302026 | E10: =C10*(1+Assumptions!$B$12) -> 1714163.1 | F10: =D10*(1+Assumptions!$B$12)*(1+Assumptions!$B$13) -> 1381319.4 | G10: =E10-F10 -> 332843.7 | H10: =IFERROR(G10/E10,0) -> 0.19417271 | I10: 72285.325 | J10: 117887.17 | K10: =E10-F10-I10-J10 -> 142671.2 | L10: =IFERROR(K10/E10,0) -> 0.083230824
A11: Jan-26 | B11: ST010 | C11: 1544021 | D11: 1204744 | E11: =C11*(1+Assumptions!$B$12) -> 1590341.6 | F11: =D11*(1+Assumptions!$B$12)*(1+Assumptions!$B$13) -> 1278112.9 | G11: =E11-F11 -> 312228.72 | H11: =IFERROR(G11/E11,0) -> 0.19632808 | I11: 75921.581 | J11: 117658.11 | K11: =E11-F11-I11-J11 -> 118649.03 | L11: =IFERROR(K11/E11,0) -> 0.074606004
A12: Jan-26 | B12: ST011 | C12: 1408002 | D12: 1111514 | E12: =C12*(1+Assumptions!$B$12) -> 1450242.1 | F12: =D12*(1+Assumptions!$B$12)*(1+Assumptions!$B$13) -> 1179205.2 | G12: =E12-F12 -> 271036.86 | H12: =IFERROR(G12/E12,0) -> 0.18689077 | I12: 72170.727 | J12: 133089.46 | K12: =E12-F12-I12-J12 -> 65776.668 | L12: =IFERROR(K12/E12,0) -> 0.045355648
A13: Jan-26 | B13: ST012 | C13: 1372555 | D13: 1105465 | E13: =C13*(1+Assumptions!$B$12) -> 1413731.7 | F13: =D13*(1+Assumptions!$B$12)*(1+Assumptions!$B$13) -> 1172787.8 | G13: =E13-F13 -> 240943.83 | H13: =IFERROR(G13/E13,0) -> 0.17043109 | I13: 71061.921 | J13: 131897.36 | K13: =E13-F13-I13-J13 -> 37984.55 | L13: =IFERROR(K13/E13,0) -> 0.026868289
A14: Jan-26 | B14: ST013 | C14: 1469056 | D14: 1167472 | E14: =C14*(1+Assumptions!$B$12) -> 1513127.7 | F14: =D14*(1+Assumptions!$B$12)*(1+Assumptions!$B$13) -> 1238571 | G14: =E14-F14 -> 274556.64 | H14: =IFERROR(G14/E14,0) -> 0.18144975 | I14: 71903.894 | J14: 120095.22 | K14: =E14-F14-I14-J14 -> 82557.522 | L14: =IFERROR(K14/E14,0) -> 0.054560843
... A291: Dec-26 | B291: ST025 | C291: 1916548 | D291: 1470751 | E291: =C291*(1+Assumptions!$B$12) -> 1974044.4 | F291: =D291*(1+Assumptions!$B$12)*(1+Assumptions!$B$13) -> 1560319.7 | G291: =E291-F291 -> 413724.7 | H291: =IFERROR(G291/E291,0) -> 0.20958226 | I291: 17329.333 | J291: 30685.863 | K291: =E291-F291-I291-J291 -> 365709.51 | L291: =IFERROR(K291/E291,0) -> 0.185259
A292: Total | C292: =SUM(C2:C291) -> 474595610 | D292: =SUM(D2:D291) -> 372380995 | E292: =SUM(E2:E291) -> 4.8883348e+08 | F292: =SUM(F2:F291) -> 3.95059e+08 | G292: =SUM(G2:G291) -> 93774481 | H292: =G292/E292 -> 0.19183318 | I292: =SUM(I2:I291) -> 16583915 | J292: =SUM(J2:J291) -> 29826040 | K292: =SUM(K2:K291) -> 47364525 | L292: =K292/E292 -> 0.096892966

Sheet historical_actuals
A1: month_year | B1: store_id | C1: net_sales | D1: cogs | E1: gross_profit | F1: gross_margin_% | G1: labour_cost | H1: operating_expenses | I1: operating_profit | J1: operating_margin_%
A2: Jan-25 | B2: ST001 | C2: 1629783 | D2: 1296230 | E2: =historical_actuals3[[#This Row],[net_sales]]-historical_actuals3[[#This Row],[cogs]] -> 333553 | F2: =IFERROR(historical_actuals3[[#This Row],[gross_profit]]/historical_actuals3[[#This Row],[net_sales]],0) -> 0.20466099 | G2: 68522.57 | H2: 134089.48 | I2: =historical_actuals3[[#This Row],[gross_profit]]-historical_actuals3[[#This Row],[labour_cost]]-historical_actuals3[[#This Row],[operating_expenses]] -> 130940.95 | J2: =IFERROR(historical_actuals3[[#This Row],[operating_profit]]/historical_actuals3[[#This Row],[net_sales]],0) -> 0.080342567
A3: Jan-25 | B3: ST002 | C3: 1617193 | D3: 1283300 | E3: =historical_actuals3[[#This Row],[net_sales]]-historical_actuals3[[#This Row],[cogs]] -> 333893 | F3: =IFERROR(historical_actuals3[[#This Row],[gross_profit]]/historical_actuals3[[#This Row],[net_sales]],0) -> 0.20646453 | G3: 67998.39 | H3: 127208.01 | I3: =historical_actuals3[[#This Row],[gross_profit]]-historical_actuals3[[#This Row],[labour_cost]]-historical_actuals3[[#This Row],[operating_expenses]] -> 138686.6 | J3: =IFERROR(historical_actuals3[[#This Row],[operating_profit]]/historical_actuals3[[#This Row],[net_sales]],0) -> 0.085757606
A4: Jan-25 | B4: ST003 | C4: 1633880 | D4: 1303972 | E4: =historical_actuals3[[#This Row],[net_sales]]-historical_actuals3[[#This Row],[cogs]] -> 329908 | F4: =IFERROR(historical_actuals3[[#This Row],[gross_profit]]/historical_actuals3[[#This Row],[net_sales]],0) -> 0.20191691 | G4: 69426.47 | H4: 125095.49 | I4: =historical_actuals3[[#This Row],[gross_profit]]-historical_actuals3[[#This Row],[labour_cost]]-historical_actuals3[[#This Row],[operating_expenses]] -> 135386.04 | J4: =IFERROR(historical_actuals3[[#This Row],[operating_profit]]/historical_actuals3[[#This Row],[net_sales]],0) -> 0.082861679
A5: Jan-25 | B5: ST004 | C5: 1620996 | D5: 1311164 | E5: =historical_actuals3[[#This Row],[net_sales]]-historical_actuals3[[#This Row],[cogs]] -> 309832 | F5: =IFERROR(historical_actuals3[[#This Row],[gross_profit]]/historical_actuals3[[#This Row],[net_sales]],0) -> 0.19113681 | G5: 66745.86 | H5: 137270.33 | I5: =historical_actuals3[[#This Row],[gross_profit]]-historical_actuals3[[#This Row],[labour_cost]]-historical_actuals3[[#This Row],[operating_expenses]] -> 105815.81 | J5: =IFERROR(historical_actuals3[[#This Row],[operating_profit]]/historical_actuals3[[#This Row],[net_sales]],0) -> 0.065278267
A6: Jan-25 | B6: ST005 | C6: 1540837 | D6: 1232753 | E6: =historical_actuals3[[#This Row],[net_sales]]-historical_actuals3[[#This Row],[cogs]] -> 308084 | F6: =IFERROR(historical_actuals3[[#This Row],[gross_profit]]/historical_actuals3[[#This Row],[net_sales]],0) -> 0.19994587 | G6: 71156.7 | H6: 119525.99 | I6: =historical_actuals3[[#This Row],[gross_profit]]-historical_actuals3[[#This Row],[labour_cost]]-historical_actuals3[[#This Row],[operating_expenses]] -> 117401.31 | J6: =IFERROR(historical_actuals3[[#This Row],[operating_profit]]/historical_actuals3[[#This Row],[net_sales]],0) -> 0.076193205
A7: Jan-25 | B7: ST006 | C7: 1490262 | D7: 1174186 | E7: =historical_actuals3[[#This Row],[net_sales]]-historical_actuals3[[#This Row],[cogs]] -> 316076 | F7: =IFERROR(historical_actuals3[[#This Row],[gross_profit]]/historical_actuals3[[#This Row],[net_sales]],0) -> 0.21209425 | G7: 70716.21 | H7: 115116.98 | I7: =historical_actuals3[[#This Row],[gross_profit]]-historical_actuals3[[#This Row],[labour_cost]]-historical_actuals3[[#This Row],[operating_expenses]] -> 130242.81 | J7: =IFERROR(historical_actuals3[[#This Row],[operating_profit]]/historical_actuals3[[#This Row],[net_sales]],0) -> 0.087395914
A8: Jan-25 | B8: ST007 | C8: 1722278 | D8: 1362688 | E8: =historical_actuals3[[#This Row],[net_sales]]-historical_actuals3[[#This Row],[cogs]] -> 359590 | F8: =IFERROR(historical_actuals3[[#This Row],[gross_profit]]/historical_actuals3[[#This Row],[net_sales]],0) -> 0.20878743 | G8: 69915.25 | H8: 112971.73 | I8: =historical_actuals3[[#This Row],[gross_profit]]-historical_actuals3[[#This Row],[labour_cost]]-historical_actuals3[[#This Row],[operating_expenses]] -> 176703.02 | J8: =IFERROR(historical_actuals3[[#This Row],[operating_profit]]/historical_actuals3[[#This Row],[net_sales]],0) -> 0.10259843
A9: Jan-25 | B9: ST008 | C9: 1766395 | D9: 1385977 | E9: =historical_actuals3[[#This Row],[net_sales]]-historical_actuals3[[#This Row],[cogs]] -> 380418 | F9: =IFERROR(historical_actuals3[[#This Row],[gross_profit]]/historical_actuals3[[#This Row],[net_sales]],0) -> 0.21536406 | G9: 69839.73 | H9: 121333.75 | I9: =historical_actuals3[[#This Row],[gross_profit]]-historical_actuals3[[#This Row],[labour_cost]]-historical_actuals3[[#This Row],[operating_expenses]] -> 189244.52 | J9: =IFERROR(historical_actuals3[[#This Row],[operating_profit]]/historical_actuals3[[#This Row],[net_sales]],0) -> 0.10713601
A10: Jan-25 | B10: ST009 | C10: 1664236 | D10: 1302026 | E10: =historical_actuals3[[#This Row],[net_sales]]-historical_actuals3[[#This Row],[cogs]] -> 362210 | F10: =IFERROR(historical_actuals3[[#This Row],[gross_profit]]/historical_actuals3[[#This Row],[net_sales]],0) -> 0.21764341 | G10: 69505.12 | H10: 114453.56 | I10: =historical_actuals3[[#This Row],[gross_profit]]-historical_actuals3[[#This Row],[labour_cost]]-historical_actuals3[[#This Row],[operating_expenses]] -> 178251.32 | J10: =IFERROR(historical_actuals3[[#This Row],[operating_profit]]/historical_actuals3[[#This Row],[net_sales]],0) -> 0.107107
A11: Jan-25 | B11: ST010 | C11: 1544021 | D11: 1204744 | E11: =historical_actuals3[[#This Row],[net_sales]]-historical_actuals3[[#This Row],[cogs]] -> 339277 | F11: =IFERROR(historical_actuals3[[#This Row],[gross_profit]]/historical_actuals3[[#This Row],[net_sales]],0) -> 0.219736 | G11: 73001.52 | H11: 114231.17 | I11: =historical_actuals3[[#This Row],[gross_profit]]-historical_actuals3[[#This Row],[labour_cost]]-historical_actuals3[[#This Row],[operating_expenses]] -> 152044.31 | J11: =IFERROR(historical_actuals3[[#This Row],[operating_profit]]/historical_actuals3[[#This Row],[net_sales]],0) -> 0.098472955
A12: Jan-25 | B12: ST011 | C12: 1408002 | D12: 1111514 | E12: =historical_actuals3[[#This Row],[net_sales]]-historical_actuals3[[#This Row],[cogs]] -> 296488 | F12: =IFERROR(historical_actuals3[[#This Row],[gross_profit]]/historical_actuals3[[#This Row],[net_sales]],0) -> 0.21057356 | G12: 69394.93 | H12: 129213.07 | I12: =historical_actuals3[[#This Row],[gross_profit]]-historical_actuals3[[#This Row],[labour_cost]]-historical_actuals3[[#This Row],[operating_expenses]] -> 97880 | J12: =IFERROR(historical_actuals3[[#This Row],[operating_profit]]/historical_actuals3[[#This Row],[net_sales]],0) -> 0.069516947
A13: Jan-25 | B13: ST012 | C13: 1372555 | D13: 1105465 | E13: =historical_actuals3[[#This Row],[net_sales]]-historical_actuals3[[#This Row],[cogs]] -> 267090 | F13: =IFERROR(historical_actuals3[[#This Row],[gross_profit]]/historical_actuals3[[#This Row],[net_sales]],0) -> 0.19459329 | G13: 68328.77 | H13: 128055.69 | I13: =historical_actuals3[[#This Row],[gross_profit]]-historical_actuals3[[#This Row],[labour_cost]]-historical_actuals3[[#This Row],[operating_expenses]] -> 70705.54 | J13: =IFERROR(historical_actuals3[[#This Row],[operating_profit]]/historical_actuals3[[#This Row],[net_sales]],0) -> 0.051513812
... A291: Dec-25 | B291: ST025 | C291: 1916548 | D291: 1470751 | E291: =historical_actuals3[[#This Row],[net_sales]]-historical_actuals3[[#This Row],[cogs]] -> 445797 | F291: =IFERROR(historical_actuals3[[#This Row],[gross_profit]]/historical_actuals3[[#This Row],[net_sales]],0) -> 0.23260414 | G291: 16662.82 | H291: 29792.1 | I291: =historical_actuals3[[#This Row],[gross_profit]]-historical_actuals3[[#This Row],[labour_cost]]-historical_actuals3[[#This Row],[operating_expenses]] -> 399342.08 | J291: =IFERROR(historical_actuals3[[#This Row],[operating_profit]]/historical_actuals3[[#This Row],[net_sales]],0) -> 0.20836529
A292: Total | C292: =SUBTOTAL(109,historical_actuals3[net_sales]) -> 474595610 | D292: =SUBTOTAL(109,historical_actuals3[cogs]) -> 372380995 | E292: =SUBTOTAL(109,historical_actuals3[gross_profit]) -> 102214615 | F292: =historical_actuals3[[#Totals],[gross_profit]]/historical_actuals3[[#Totals],[net_sales]] -> 0.21537202 | G292: =SUBTOTAL(109,historical_actuals3[labour_cost]) -> 15946072 | H292: =SUBTOTAL(109,historical_actuals3[operating_expenses]) -> 28957321 | I292: =SUBTOTAL(109,historical_actuals3[operating_profit]) -> 57311222 | J292: =historical_actuals3[[#Totals],[operating_profit]]/historical_actuals3[[#Totals],[net_sales]] -> 0.12075801

Sheet Assumptions
A2: Selected Scenario | B2: Base
A5: Assumption | B5: Downside | C5: Base | D5: Upside
A6: Sales Growth % | B6: -0.02 | C6: 0.03 | D6: 0.06
A7: COGS Inflation % | B7: 0.05 | C7: 0.03 | D7: 0.01
A8: Labour Cost Increase % | B8: 0.06 | C8: 0.04 | D8: 0.03
A9: Operating Expense Increase % | B9: 0.05 | C9: 0.03 | D9: 0.02
A11: Assumption | B11: Selected Value
A12: Sales Growth % | B12: =_xlfn.XLOOKUP($B$2,$B$5:$D$5,B6:D6) -> 0.03
A13: COGS Inflation % | B13: =_xlfn.XLOOKUP($B$2,$B$5:$D$5,B7:D7) -> 0.03
A14: Labour Cost Increase % | B14: =_xlfn.XLOOKUP($B$2,$B$5:$D$5,B8:D8) -> 0.04
A15: Operating Expense Increase % | B15: =_xlfn.XLOOKUP($B$2,$B$5:$D$5,B9:D9) -> 0.03

Sheet raw_data
A1: month_year | B1: store_id | C1: net_sales | D1: cogs | E1: labour_cost | F1: operating_expenses
A2: Jan-25 | B2: ST001 | C2: 1629783 | D2: 1296230 | E2: 68522.57 | F2: 134089.48
A3: Jan-25 | B3: ST002 | C3: 1617193 | D3: 1283300 | E3: 67998.39 | F3: 127208.01
A4: Jan-25 | B4: ST003 | C4: 1633880 | D4: 1303972 | E4: 69426.47 | F4: 125095.49
A5: Jan-25 | B5: ST004 | C5: 1620996 | D5: 1311164 | E5: 66745.86 | F5: 137270.33
A6: Jan-25 | B6: ST005 | C6: 1540837 | D6: 1232753 | E6: 71156.7 | F6: 119525.99
A7: Jan-25 | B7: ST006 | C7: 1490262 | D7: 1174186 | E7: 70716.21 | F7: 115116.98
A8: Jan-25 | B8: ST007 | C8: 1722278 | D8: 1362688 | E8: 69915.25 | F8: 112971.73
A9: Jan-25 | B9: ST008 | C9: 1766395 | D9: 1385977 | E9: 69839.73 | F9: 121333.75
A10: Jan-25 | B10: ST009 | C10: 1664236 | D10: 1302026 | E10: 69505.12 | F10: 114453.56
A11: Jan-25 | B11: ST010 | C11: 1544021 | D11: 1204744 | E11: 73001.52 | F11: 114231.17
A12: Jan-25 | B12: ST011 | C12: 1408002 | D12: 1111514 | E12: 69394.93 | F12: 129213.07
A13: Jan-25 | B13: ST012 | C13: 1372555 | D13: 1105465 | E13: 68328.77 | F13: 128055.69
... A291: Dec-25 | B291: ST025 | C291: 1916548 | D291: 1470751 | E291: 16662.82 | F291: 29792.1

Sheet 2026_Plan_sales
B1: =Assumptions!$B$2 -> Base
A3: month_year | B3: store_id | C3: 2025_sales | D3: planned_sales_2026
A4: {=_xlfn.HSTACK(SUBSTITUTE(historical_actuals[month_year],"-25","-26"),historical_actuals[store_id],historical_actuals[net_sales])} -> Jan-26 | B4: ST001 | C4: 1629783 | D4: =C4*(1+Assumptions!$B$12) -> 1678676.5
A5: Jan-26 | B5: ST002 | C5: 1617193 | D5: =C5*(1+Assumptions!$B$12) -> 1665708.8
A6: Jan-26 | B6: ST003 | C6: 1633880 | D6: =C6*(1+Assumptions!$B$12) -> 1682896.4
A7: Jan-26 | B7: ST004 | C7: 1620996 | D7: =C7*(1+Assumptions!$B$12) -> 1669625.9
A8: Jan-26 | B8: ST005 | C8: 1540837 | D8: =C8*(1+Assumptions!$B$12) -> 1587062.1
A9: Jan-26 | B9: ST006 | C9: 1490262 | D9: =C9*(1+Assumptions!$B$12) -> 1534969.9
A10: Jan-26 | B10: ST007 | C10: 1722278 | D10: =C10*(1+Assumptions!$B$12) -> 1773946.3
A11: Jan-26 | B11: ST008 | C11: 1766395 | D11: =C11*(1+Assumptions!$B$12) -> 1819386.9
A12: Jan-26 | B12: ST009 | C12: 1664236 | D12: =C12*(1+Assumptions!$B$12) -> 1714163.1
A13: Jan-26 | B13: ST010 | C13: 1544021 | D13: =C13*(1+Assumptions!$B$12) -> 1590341.6
A14: Jan-26 | B14: ST011 | C14: 1408002 | D14: =C14*(1+Assumptions!$B$12) -> 1450242.1
A15: Jan-26 | B15: ST012 | C15: 1372555 | D15: =C15*(1+Assumptions!$B$12) -> 1413731.7
A16: Jan-26 | B16: ST013 | C16: 1469056 | D16: =C16*(1+Assumptions!$B$12) -> 1513127.7
... A293: Dec-26 | B293: ST025 | C293: 1916548 | D293: =C293*(1+Assumptions!$B$12) -> 1974044.4
